csiro_spectral_tools-0.2.1.dist-info/top_level.txt
csiro_spectral_tools-0.2.1.dist-info/LICENSE
csiro_spectral_tools-0.2.1.dist-info/RECORD
csiro_spectral_tools-0.2.1.dist-info/WHEEL
csiro_spectral_tools-0.2.1.dist-info/METADATA
csiro_spectral_tools/__init__.py
csiro_spectral_tools/io/parse_tsg.py
csiro_spectral_tools/io/parse_csv.py
csiro_spectral_tools/io/__init__.py
csiro_spectral_tools/io/parse_numpy.py
csiro_spectral_tools/io/parse_envi.py
csiro_spectral_tools/hulls/__init__.py
csiro_spectral_tools/hulls/convexhulls.py
csiro_spectral_tools/hulls/phull.py
csiro_spectral_tools/extraction/__init__.py
csiro_spectral_tools/extraction/extraction.py
csiro_spectral_tools/ext/__init__.py
csiro_spectral_tools/ext/chulls.cpython-311-x86_64-linux-gnu.so
csiro_spectral_tools/ext/setup.py
csiro_spectral_tools/ext/chulls.c
