Metadata-Version: 2.1
Name: csiro-spectral-tools
Version: 0.2.1
Summary: A collection of tools used for working with hyperspectral data
Home-page: https://github.com/CSIRO-GeoscienceAnalytics/spectral-tools
Author: Andrew Rodger
License: MIT
Requires-Python: >=3.8
License-File: LICENSE
Requires-Dist: numpy
Requires-Dist: spectral
Requires-Dist: pandas
Requires-Dist: scipy
Requires-Dist: scikit-learn
